{"id": "267e23b2-bbf4-4c67-a125-3168e728ff57", "code": "# EVOLVE-BLOCK-START\ndef score(age, frequency, recency, size, cache_size, now):\n    \"\"\"Higher score = keep; lowest-scored resident is evicted.\n    age        = now - insert_time\n    frequency  = total access count while resident\n    recency    = now - last_access_time\n    size       = item size (1 in the uniform-cost experiments)\n    cache_size = capacity (constant within a run)\n    now        = current logical timestamp\n    \n    Strategy: Balanced hybrid optimized for Churn and Stable Frequency.\n    - 0.8 * frequency: Reduced weight to prevent hoarding stale popular items (helps Churn).\n    - 4.0 * recency: High weight for recent access (beats LRU on Temporal Locality).\n    - 2.0 * age: Stronger penalty for staleness (forces eviction of old items in Churn).\n    This shift from pure popularity to recency-aware retention improves overall fitness.\n    \"\"\"\n    return 0.8 * frequency + 4.0 * recency - 2.0 * age\n# EVOLVE-BLOCK-END", "changes_description": null, "language": "python", "parent_id": "d1868aba-ecd2-4f74-ad0d-5291fdc70016", "generation": 7, "timestamp": 1782572841.3308196, "iteration_found": 47, "metrics": {"combined_score": 0.0}, "complexity": 0.0, "diversity": 0.0, "metadata": {"changes": "Full rewrite", "parent_metrics": {"churn_hitrate": 0.2269375, "combined_score": 0.0, "temporal_locality_hitrate": 0.0836875, "stable_frequency_hitrate": 0.136375, "scan_hitrate": 0.2485}, "island": 1}, "prompts": null, "artifacts_json": null, "artifact_dir": null, "embedding": null}