{"id": "d95a462f-2090-46a4-83cb-20a3806d2682", "code": "def score(age, frequency, recency, size, cache_size, now):\n    return - ((age + 1.1 * recency + 0.2 * frequency) ** 1.2 / (age + 1) + (frequency ** 0.7) / (age + 1) ** 1.1)", "changes_description": null, "language": "python", "parent_id": "2350c509-73be-4438-b5e3-bcb1afccbc57", "generation": 3, "timestamp": 1782660936.8001783, "iteration_found": 0, "metrics": {"combined_score": -0.20066673246156522, "stable_frequency_hitrate": 0.6124791666666667, "churn_hitrate": 0.3072708333333333}, "complexity": 0.0, "diversity": 0.0, "metadata": {"changes": "Full rewrite", "parent_metrics": {"combined_score": -1.4484555425984604, "stable_frequency_hitrate": 0.44797916666666676, "churn_hitrate": 0.3061041666666667}, "island": 3, "migrant": true}, "prompts": null, "artifacts_json": null, "artifact_dir": null, "embedding": null}