{"id": "19e87e58-2daa-4096-afda-6a2773dc0eed", "code": "\"\"\"\nSeed program for the cache-replacement-policy evolution experiment.\n\nOpenEvolve mutates ONLY the `score()` function inside the EVOLVE-BLOCK. The fixed\n`simulate()` harness below calls it on every eviction and must not be changed \u2014 it\nis the contract the evaluator depends on (see IMPLEMENTATION.md \u00a7A).\n\n`score(...)` returns a value where HIGHER = more valuable = keep; the lowest-scored\nresident is evicted. The seed `-recency` reproduces LRU exactly, so generation 0 is a\nknown-good baseline (the evaluator scores it 0.0 = no gain over LRU).\n\"\"\"\n\n# EVOLVE-BLOCK-START\ndef score(age, frequency, recency, size, cache_size, now):\n    \"\"\"\n    Optimized Hybrid ARC Policy.\n    \n    Strategy:\n    - Recency (1.0): Dominant driver for temporal locality. Ensures recently accessed items stay.\n    - Frequency (0.6): Increased weight to better retain popular items in stable workloads.\n      Helps prevent evicting stable items that have slight gaps in access.\n    - Age (0.1): Reduced penalty compared to previous version. Allows items to stay longer \n      if they are popular, which helps in temporal cycles. In churn workloads, this prevents \n      premature eviction of items that are naturally 'old' but still relevant due to frequency/recency.\n    \"\"\"\n    return recency + frequency * 0.6 + age * 0.1\n# EVOLVE-BLOCK-END\n\n\ndef simulate(trace, capacity):\n    \"\"\"Fixed trace-driven simulator. Returns the hit rate of `score()` on `trace`\n    at the given cache `capacity`. Not evolved.\"\"\"\n    cache = {}  # key -> [insert_time, last_access, freq, size]\n    hits = 0\n    for now, key in enumerate(trace):\n        m = cache.get(key)\n        if m is not None:\n            hits += 1\n            m[1] = now\n            m[2] += 1\n        else:\n            if len(cache) >= capacity:\n                victim = min(\n                    cache,\n                    key=lambda k: score(\n                        now - cache[k][0], cache[k][2], now - cache[k][1],\n                        cache[k][3], capacity, now,\n                    ),\n                )\n                del cache[victim]\n            cache[key] = [now, now, 1, 1]\n    return hits / len(trace)\n\n\nif __name__ == \"__main__\":\n    # Tiny self-check: seed must behave like LRU on a simple reuse pattern.\n    trace = [1, 2, 3, 1, 2, 3, 4, 1, 2, 3]\n    print(\"hit rate @cap2:\", simulate(trace, 2))", "changes_description": null, "language": "python", "parent_id": "8a8c49c1-608c-4867-90fa-09e90866c021", "generation": 5, "timestamp": 1782576483.1681466, "iteration_found": 166, "metrics": {"churn_hitrate": 0.2069375, "combined_score": 0.27415005760119193, "temporal_locality_hitrate": 0.0975, "stable_frequency_hitrate": 0.5959375, "scan_hitrate": 0.49375}, "complexity": 0.0, "diversity": 0.0, "metadata": {"changes": "Full rewrite", "parent_metrics": {"churn_hitrate": 0.2076875, "combined_score": 0.27415005760119193, "temporal_locality_hitrate": 0.098375, "stable_frequency_hitrate": 0.5959375, "scan_hitrate": 0.49375}, "island": 3}, "prompts": {"full_rewrite_user": {"system": "You are an expert systems engineer designing cache eviction policies.\nYou modify a single Python function:\n    score(age, frequency, recency, size, cache_size, now) -> float\nThe cache evicts the item with the LOWEST score. Combine recency, frequency and\nage to beat LRU/LFU/ARC across diverse workloads (temporal locality, stable\nfrequency, scan, churn). Keep it a short, pure arithmetic expression.\n", "user": "# Current Program Information\n- Fitness: 0.2742\n- Feature coordinates: stable_frequency_hitrate=0.60, churn_hitrate=0.21\n- Focus areas: - Fitness unchanged at 0.2742\n- Exploring stable_frequency_hitrate=0.60, churn_hitrate=0.21 region of solution space\n- Consider simplifying - code length exceeds 500 characters\n\n## Last Execution Output\n\n### hit_rate_table\n```\nworkload            cap    cand    LRU    LFU    ARC    OPT     gap\ntemporal_locality    64  0.069  0.554  0.119  0.579  0.705   0.000\ntemporal_locality   256  0.128  0.705  0.304  0.699  0.705     n/a\nstable_frequency     64  0.514  0.500  0.585  0.583  0.666   0.085\nstable_frequency    256  0.678  0.666  0.709  0.712  0.775   0.108\nscan                 64  0.494  0.487  0.494  0.494  0.494   1.000\nscan                256  0.494  0.487  0.494  0.494  0.494   1.000\nchurn                64  0.090  0.131  0.093  0.125  0.434   0.000\nchurn               256  0.326  0.494  0.352  0.494  0.771   0.000\n```\n\n# Program Evolution History\n## Previous Attempts\n\n### Attempt 2\n- Changes: Full rewrite\n- Metrics: churn_hitrate: 0.2069, combined_score: 0.2742, temporal_locality_hitrate: 0.0975, stable_frequency_hitrate: 0.5959, scan_hitrate: 0.4938\n- Outcome: Mixed results\n\n### Attempt 1\n- Changes: Full rewrite\n- Metrics: churn_hitrate: 0.2287, combined_score: 0.3655, temporal_locality_hitrate: 0.2418, stable_frequency_hitrate: 0.6484, scan_hitrate: 0.4938\n- Outcome: Mixed results\n\n## Top Performing Programs\n\n### Program 1 (Score: 0.3655)\n```python\n\"\"\"\nSeed program for the cache-replacement-policy evolution experiment.\n\nOpenEvolve mutates ONLY the `score()` function inside the EVOLVE-BLOCK. The fixed\n`simulate()` harness below calls it on every eviction and must not be changed \u2014 it\nis the contract the evaluator depends on (see IMPLEMENTATION.md \u00a7A).\n\n`score(...)` returns a value where HIGHER = more valuable = keep; the lowest-scored\nresident is evicted. The seed `-recency` reproduces LRU exactly, so generation 0 is a\nknown-good baseline (the evaluator scores it 0.0 = no gain over LRU).\n\"\"\"\n\n# EVOLVE-BLOCK-START\ndef score(age, frequency, recency, size, cache_size, now):\n    \"\"\"Higher score = keep; lowest-scored resident is evicted.\n    age        = now - insert_time\n    frequency  = total access count while resident\n    recency    = now - last_access_time\n    size       = item size (1 in the uniform-cost experiments)\n    cache_size = capacity (constant within a run)\n    now        = current logical timestamp\n    \"\"\"\n    # Optimized balanced weighting for diverse workloads:\n    # - frequency (w=1.0): Favors items with history (stable_frequency).\n    # - recency_term (w=2.0): Amplified inverse recency for temporal locality.\n    # - age_penalty (w=1.0, normalized): Penalty relative to 'now'.\n    #   Normalizing age by 'now' prevents \"old\" items from being unfairly evicted\n    #   in churn workloads where absolute age is high but relative age is stable.\n    #   This balances scan eviction (high age penalty) with churn retention (stable age).\n    return frequency + (2.0 / (recency + 1)) - (age / (now + 1))\n# EVOLVE-BLOCK-END\n\n\ndef simulate(trace, capacity):\n    \"\"\"Fixed trace-driven simulator. Returns the hit rate of `score()` on `trace`\n    at the given cache `capacity`. Not evolved.\"\"\"\n    cache = {}  # key -> [insert_time, last_access, freq, size]\n    hits = 0\n    for now, key in enumerate(trace):\n        m = cache.get(key)\n        if m is not None:\n            hits += 1\n            m[1] = now\n            m[2] += 1\n        else:\n            if len(cache) >= capacity:\n                victim = min(\n                    cache,\n                    key=lambda k: score(\n                        now - cache[k][0], cache[k][2], now - cache[k][1],\n                        cache[k][3], capacity, now,\n                    ),\n                )\n                del cache[victim]\n            cache[key] = [now, now, 1, 1]\n    return hits / len(trace)\n\n\nif __name__ == \"__main__\":\n    # Tiny self-check: seed must behave like LRU on a simple reuse pattern.\n    trace = [1, 2, 3, 1, 2, 3, 4, 1, 2, 3]\n    print(\"hit rate @cap2:\", simulate(trace, 2))\n```\nKey features: Performs well on churn_hitrate (0.2287), Performs well on combined_score (0.3655), Performs well on temporal_locality_hitrate (0.2418), Performs well on stable_frequency_hitrate (0.6484), Performs well on scan_hitrate (0.4938)\n\n### Program 2 (Score: 0.2742)\n```python\n\"\"\"\nSeed program for the cache-replacement-policy experiment.\n\nOpenEvolve mutates ONLY the `score()` function inside the EVOLVE-BLOCK.\n\n`score(...)` returns a value where HIGHER = more valuable = keep.\nThe seed implements a tuned Hybrid ARC policy.\n\"\"\"\n\n# EVOLVE-BLOCK-START\ndef score(age, frequency, recency, size, cache_size, now):\n    \"\"\"\n    Tuned Hybrid ARC Policy.\n    \n    Strategy:\n    - Recency (1.0): Primary driver for temporal locality. Ensures recently accessed items stay.\n    - Frequency (0.4): Moderate boost for stable popularity. Helps keep popular items \n      that haven't been accessed in the immediate last step.\n    - Age (0.1): Minor penalty for staleness. Helps clear out old items in churn/scan \n      workloads without prematurely evicting items in temporal cycles.\n    \"\"\"\n    return recency + frequency * 0.4 + age * 0.1\n# EVOLVE-BLOCK-END\n\n\ndef simulate(trace, capacity):\n    \"\"\"Fixed trace-driven simulator. Returns the hit rate of `score()` on `trace`\n    at the given cache `capacity`. Not evolved.\"\"\"\n    cache = {}  # key -> [insert_time, last_access, freq, size]\n    hits = 0\n    for now, key in enumerate(trace):\n        m = cache.get(key)\n        if m is not None:\n            hits += 1\n            m[1] = now\n            m[2] += 1\n        else:\n            if len(cache) >= capacity:\n                victim = min(\n                    cache,\n                    key=lambda k: score(\n                        now - cache[k][0], cache[k][2], now - cache[k][1],\n                        cache[k][3], capacity, now,\n                    ),\n                )\n                del cache[victim]\n            cache[key] = [now, now, 1, 1]\n    return hits / len(trace)\n\n\nif __name__ == \"__main__\":\n    # Tiny self-check: seed must behave like LRU on a simple reuse pattern.\n    trace = [1, 2, 3, 1, 2, 3, 4, 1, 2, 3]\n    print(\"hit rate @cap2:\", simulate(trace, 2))\n```\nKey features: Performs well on churn_hitrate (0.2069), Performs well on combined_score (0.2742), Performs well on temporal_locality_hitrate (0.0975), Performs well on stable_frequency_hitrate (0.5959), Performs well on scan_hitrate (0.4938)\n\n\n\n## Diverse Programs\n\n### Program D1 (Score: 0.2742)\n```python\n\"\"\"\nSeed program for the cache-replacement-policy evolution experiment.\n\nOpenEvolve mutates ONLY the `score()` function inside the EVOLVE-BLOCK. The fixed\n`simulate()` harness below calls it on every eviction and must not be changed \u2014 it\nis the contract the evaluator depends on (see IMPLEMENTATION.md \u00a7A).\n\n`score(...)` returns a value where HIGHER = more valuable = keep; the lowest-scored\nresident is evicted. The seed `-recency` reproduces LRU exactly, so generation 0 is a\nknown-good baseline (the evaluator scores it 0.0 = no gain over LRU).\n\"\"\"\n\n# EVOLVE-BLOCK-START\ndef score(age, frequency, recency, size, cache_size, now):\n    \"\"\"Higher score = keep; lowest-scored resident is evicted.\n    age        = now - insert_time\n    frequency  = total access count while resident\n    recency    = now - last_access_time\n    size       = item size (1 in the uniform-cost experiments)\n    cache_size = capacity (constant within a run)\n    now        = current logical timestamp\n    \n    Strategy: Hybrid ARC-like policy.\n    - Recency dominates to capture temporal locality (recently accessed items stay).\n    - Frequency adds substantial weight to capture stable popularity.\n    - Age adds a small penalty to clear out stale items during churn.\n    \"\"\"\n    # Weighted combination:\n    # recency is the primary driver for temporal locality.\n    # frequency is boosted to prevent evicting popular items that haven't been accessed in the very last step.\n    # age is a minor penalty to help with churn workloads.\n    return recency + frequency * 0.5 + age * 0.1\n# EVOLVE-BLOCK-END\n\n\ndef simulate(trace, capacity):\n    \"\"\"Fixed trace-driven simulator. Returns the hit rate of `score()` on `trace`\n    at the given cache `capacity`. Not evolved.\"\"\"\n    cache = {}  # key -> [insert_time, last_access, freq, size]\n    hits = 0\n    for now, key in enumerate(trace):\n        m = cache.get(key)\n        if m is not None:\n            hits += 1\n            m[1] = now\n            m[2] += 1\n        else:\n            if len(cache) >= capacity:\n                victim = min(\n                    cache,\n                    key=lambda k: score(\n                        now - cache[k][0], cache[k][2], now - cache[k][1],\n                        cache[k][3], capacity, now,\n                    ),\n                )\n                del cache[victim]\n            cache[key] = [now, now, 1, 1]\n    return hits / len(trace)\n\n\nif __name__ == \"__main__\":\n    # Tiny self-check: seed must behave like LRU on a simple reuse pattern.\n    trace = [1, 2, 3, 1, 2, 3, 4, 1, 2, 3]\n    print(\"hit rate @cap2:\", simulate(trace, 2))\n```\nKey features: Alternative approach to churn_hitrate, Alternative approach to combined_score\n\n## Inspiration Programs\n\nThese programs represent diverse approaches and creative solutions that may inspire new ideas:\n\n### Inspiration 1 (Score: 0.2742, Type: Exploratory)\n```python\n\"\"\"\nSeed program for the cache-replacement-policy experiment.\n\nOpenEvolve mutates ONLY the `score()` function inside the EVOLVE-BLOCK.\n\n`score(...)` returns a value where HIGHER = more valuable = keep.\nThe seed implements a tuned Hybrid ARC policy.\n\"\"\"\n\n# EVOLVE-BLOCK-START\ndef score(age, frequency, recency, size, cache_size, now):\n    \"\"\"\n    Tuned Hybrid ARC Policy.\n    \n    Strategy:\n    - Recency (1.0): Primary driver for temporal locality. Ensures recently accessed items stay.\n    - Frequency (0.4): Moderate boost for stable popularity. Helps keep popular items \n      that haven't been accessed in the immediate last step.\n    - Age (0.1): Minor penalty for staleness. Helps clear out old items in churn/scan \n      workloads without prematurely evicting items in temporal cycles.\n    \"\"\"\n    return recency + frequency * 0.4 + age * 0.1\n# EVOLVE-BLOCK-END\n\n\ndef simulate(trace, capacity):\n    \"\"\"Fixed trace-driven simulator. Returns the hit rate of `score()` on `trace`\n    at the given cache `capacity`. Not evolved.\"\"\"\n    cache = {}  # key -> [insert_time, last_access, freq, size]\n    hits = 0\n    for now, key in enumerate(trace):\n        m = cache.get(key)\n        if m is not None:\n            hits += 1\n            m[1] = now\n            m[2] += 1\n        else:\n            if len(cache) >= capacity:\n                victim = min(\n                    cache,\n                    key=lambda k: score(\n                        now - cache[k][0], cache[k][2], now - cache[k][1],\n                        cache[k][3], capacity, now,\n                    ),\n                )\n                del cache[victim]\n            cache[key] = [now, now, 1, 1]\n    return hits / len(trace)\n\n\nif __name__ == \"__main__\":\n    # Tiny self-check: seed must behave like LRU on a simple reuse pattern.\n    trace = [1, 2, 3, 1, 2, 3, 4, 1, 2, 3]\n    print(\"hit rate @cap2:\", simulate(trace, 2))\n```\nUnique approach: Modification:, [Fragment formatting error: 'metric_name']\n\n### Inspiration 2 (Score: 0.2500, Type: Exploratory)\n```python\n\"\"\"\nSeed program for the cache-replacement-policy evolution experiment.\n\nOpenEvolve mutates ONLY the `score()` function inside the EVOLVE-BLOCK. The fixed\n`simulate()` harness below calls it on every eviction and must not be changed \u2014 it\nis the contract the evaluator depends on (see IMPLEMENTATION.md \u00a7A).\n\n`score(...)` returns a value where HIGHER = more valuable = keep; the lowest-scored\nresident is evicted. The seed `-recency` reproduces LRU exactly, so generation 0 is a\nknown-good baseline (the evaluator scores it 0.0 = no gain over LRU).\n\"\"\"\n\n# EVOLVE-BLOCK-START\ndef score(age, frequency, recency, size, cache_size, now):\n    \"\"\"Higher score = keep; lowest-scored resident is evicted.\n    age        = now - insert_time\n    frequency  = total access count while resident\n    recency    = now - last_access_time\n    size       = item size (1 in the uniform-cost experiments)\n    cache_size = capacity (constant within a run)\n    now        = current logical timestamp\n    \n    Strategy: Balanced Hybrid ARC with normalized age.\n    - Recency (1.0) dominates to capture temporal locality.\n    - Frequency (0.5) is boosted to retain popular items in stable workloads.\n    - Age penalty is normalized by trace length (now) to prevent it from becoming\n      disproportionately large in long traces, aiding churn and scan handling.\n    \"\"\"\n    # Normalized age penalty: prevents absolute age from dominating in long traces.\n    # Frequency boost: better retention of stable items.\n    return recency + frequency * 0.5 + age / (now + 1) * 0.1\n# EVOLVE-BLOCK-END\n\n\ndef simulate(trace, capacity):\n    \"\"\"Fixed trace-driven simulator. Returns the hit rate of `score()` on `trace`\n    at the given cache `capacity`. Not evolved.\"\"\"\n    cache = {}  # key -> [insert_time, last_access, freq, size]\n    hits = 0\n    for now, key in enumerate(trace):\n        m = cache.get(key)\n        if m is not None:\n            hits += 1\n            m[1] = now\n            m[2] += 1\n        else:\n            if len(cache) >= capacity:\n                victim = min(\n                    cache,\n                    key=lambda k: score(\n                        now - cache[k][0], cache[k][2], now - cache[k][1],\n                        cache[k][3], capacity, now,\n                    ),\n                )\n                del cache[victim]\n            cache[key] = [now, now, 1, 1]\n    return hits / len(trace)\n\n\nif __name__ == \"__main__\":\n    # Tiny self-check: seed must behave like LRU on a simple reuse pattern.\n    trace = [1, 2, 3, 1, 2, 3, 4, 1, 2, 3]\n    print(\"hit rate @cap2:\", simulate(trace, 2))\n```\nUnique approach: Modification:, [Fragment formatting error: 'metric_name']\n\n# Current Program\n```python\n\"\"\"\nSeed program for the cache-replacement-policy evolution experiment.\n\nOpenEvolve mutates ONLY the `score()` function inside the EVOLVE-BLOCK. The fixed\n`simulate()` harness below calls it on every eviction and must not be changed \u2014 it\nis the contract the evaluator depends on (see IMPLEMENTATION.md \u00a7A).\n\n`score(...)` returns a value where HIGHER = more valuable = keep; the lowest-scored\nresident is evicted. The seed `-recency` reproduces LRU exactly, so generation 0 is a\nknown-good baseline (the evaluator scores it 0.0 = no gain over LRU).\n\"\"\"\n\n# EVOLVE-BLOCK-START\ndef score(age, frequency, recency, size, cache_size, now):\n    \"\"\"\n    Optimized Hybrid ARC Policy.\n    \n    Strategy:\n    - Recency (1.0): Dominant driver for temporal locality. Ensures recently accessed items stay.\n    - Frequency (0.4): Increased weight to better retain popular items in stable workloads.\n      Helps prevent evicting stable items that have slight gaps in access.\n    - Age (0.3): Reduced penalty compared to previous version. Allows items to stay longer \n      if they are popular, which helps in temporal cycles (e.g., 1->2->1) where an item \n      might be old but about to be reused.\n    \"\"\"\n    return recency + frequency * 0.4 + age * 0.3\n# EVOLVE-BLOCK-END\n\n\ndef simulate(trace, capacity):\n    \"\"\"Fixed trace-driven simulator. Returns the hit rate of `score()` on `trace`\n    at the given cache `capacity`. Not evolved.\"\"\"\n    cache = {}  # key -> [insert_time, last_access, freq, size]\n    hits = 0\n    for now, key in enumerate(trace):\n        m = cache.get(key)\n        if m is not None:\n            hits += 1\n            m[1] = now\n            m[2] += 1\n        else:\n            if len(cache) >= capacity:\n                victim = min(\n                    cache,\n                    key=lambda k: score(\n                        now - cache[k][0], cache[k][2], now - cache[k][1],\n                        cache[k][3], capacity, now,\n                    ),\n                )\n                del cache[victim]\n            cache[key] = [now, now, 1, 1]\n    return hits / len(trace)\n\n\nif __name__ == \"__main__\":\n    # Tiny self-check: seed must behave like LRU on a simple reuse pattern.\n    trace = [1, 2, 3, 1, 2, 3, 4, 1, 2, 3]\n    print(\"hit rate @cap2:\", simulate(trace, 2))\n```\n\n# Task\nRewrite the program to improve its FITNESS SCORE.\nThe system maintains diversity across these dimensions: stable_frequency_hitrate, churn_hitrate\nDifferent solutions with similar fitness but different features are valuable.\nProvide the complete new program code.\n\nIMPORTANT: Make sure your rewritten program maintains the same inputs and outputs\nas the original program, but with improved internal implementation.\n\n```python\n# Your rewritten program here\n```", "responses": ["To improve the fitness score and address the specific focus areas (`stable_frequency_hitrate` and `churn_hitrate`), we need to refine the balance between **Recency**, **Frequency**, and **Age**.\n\n### Analysis of Current State\n- **Current Score**: 0.2742\n- **Focus Areas**: `stable_frequency_hitrate=0.60`, `churn_hitrate=0.21`\n- **Issue**: The current program (`recency + freq*0.4 + age*0.3`) likely suffers from:\n  1.  **Stable Frequency**: While frequency is weighted, simply adding it linearly might not be enough to distinguish \"stable\" popular items from \"recently accessed but unstable\" items in all scenarios. A higher weight or normalization helps.\n  2.  **Churn**: In churn workloads, items disappear quickly. A linear `age` penalty (`+ age * 0.3`) might be too weak to evict truly stale items that are no longer relevant, or conversely, if the weights are unbalanced, it might hold onto items that should have been evicted earlier.\n  3.  **Temporal Locality**: The `recency` term is the primary driver here. This is good for temporal locality but might conflict with frequency-based policies.\n\n### Proposed Solution\nWe adjust the weights to create a more robust hybrid policy:\n1.  **Increase Frequency Weight**: Boosting frequency from `0.4` to `0.6` helps retain items that are popular over time (stable workloads), which is crucial for `stable_frequency_hitrate`.\n2.  **Reduce Age Weight**: Lowering the age penalty from `0.3` to `0.1` prevents the policy from prematurely evicting items that are currently \"old\" (large `age`) but have high frequency or recent access. In churn scenarios, items often have high absolute age; a lower penalty allows the `recency` and `frequency` signals to dominate, ensuring we only evict items that are *both* old and unpopular.\n3.  **Maintain Recency Dominance**: Keep `recency` as the base (weight 1.0) to ensure strong temporal locality performance, which is generally the baseline requirement.\n\nThis combination (`recency + freq*0.6 + age*0.1`) creates a policy that:\n-   Prioritizes recently used items (LRU-like).\n-   Strongly favors items with a history of accesses (LFU-like) for stability.\n-   Minimizes the raw age penalty, allowing the cache to focus on relative recency and frequency rather than absolute insertion time, which improves performance in churn scenarios where items naturally have high ages.\n\n```python\n\"\"\"\nSeed program for the cache-replacement-policy evolution experiment.\n\nOpenEvolve mutates ONLY the `score()` function inside the EVOLVE-BLOCK. The fixed\n`simulate()` harness below calls it on every eviction and must not be changed \u2014 it\nis the contract the evaluator depends on (see IMPLEMENTATION.md \u00a7A).\n\n`score(...)` returns a value where HIGHER = more valuable = keep; the lowest-scored\nresident is evicted. The seed `-recency` reproduces LRU exactly, so generation 0 is a\nknown-good baseline (the evaluator scores it 0.0 = no gain over LRU).\n\"\"\"\n\n# EVOLVE-BLOCK-START\ndef score(age, frequency, recency, size, cache_size, now):\n    \"\"\"\n    Optimized Hybrid ARC Policy.\n    \n    Strategy:\n    - Recency (1.0): Dominant driver for temporal locality. Ensures recently accessed items stay.\n    - Frequency (0.6): Increased weight to better retain popular items in stable workloads.\n      Helps prevent evicting stable items that have slight gaps in access.\n    - Age (0.1): Reduced penalty compared to previous version. Allows items to stay longer \n      if they are popular, which helps in temporal cycles. In churn workloads, this prevents \n      premature eviction of items that are naturally 'old' but still relevant due to frequency/recency.\n    \"\"\"\n    return recency + frequency * 0.6 + age * 0.1\n# EVOLVE-BLOCK-END\n\n\ndef simulate(trace, capacity):\n    \"\"\"Fixed trace-driven simulator. Returns the hit rate of `score()` on `trace`\n    at the given cache `capacity`. Not evolved.\"\"\"\n    cache = {}  # key -> [insert_time, last_access, freq, size]\n    hits = 0\n    for now, key in enumerate(trace):\n        m = cache.get(key)\n        if m is not None:\n            hits += 1\n            m[1] = now\n            m[2] += 1\n        else:\n            if len(cache) >= capacity:\n                victim = min(\n                    cache,\n                    key=lambda k: score(\n                        now - cache[k][0], cache[k][2], now - cache[k][1],\n                        cache[k][3], capacity, now,\n                    ),\n                )\n                del cache[victim]\n            cache[key] = [now, now, 1, 1]\n    return hits / len(trace)\n\n\nif __name__ == \"__main__\":\n    # Tiny self-check: seed must behave like LRU on a simple reuse pattern.\n    trace = [1, 2, 3, 1, 2, 3, 4, 1, 2, 3]\n    print(\"hit rate @cap2:\", simulate(trace, 2))\n```"]}}, "artifacts_json": "{\"hit_rate_table\": \"workload            cap    cand    LRU    LFU    ARC    OPT     gap\\ntemporal_locality    64  0.069  0.554  0.119  0.579  0.705   0.000\\ntemporal_locality   256  0.126  0.705  0.304  0.699  0.705     n/a\\nstable_frequency     64  0.514  0.500  0.585  0.583  0.666   0.085\\nstable_frequency    256  0.678  0.666  0.709  0.712  0.775   0.108\\nscan                 64  0.494  0.487  0.494  0.494  0.494   1.000\\nscan                256  0.494  0.487  0.494  0.494  0.494   1.000\\nchurn                64  0.090  0.131  0.093  0.125  0.434   0.000\\nchurn               256  0.324  0.494  0.352  0.494  0.771   0.000\"}", "artifact_dir": null, "embedding": null}