{"id": "f5b5cc77-ccf3-464b-a04e-d0dfe6fa6c5e", "code": "def score(age, frequency, recency, size, cache_size, now):\n    return -((recency / (age + 1)) + (1 / (frequency + 1)) * ((age + 1.2 * recency + 0.05 * frequency) ** 0.8))", "changes_description": null, "language": "python", "parent_id": "8c56ec47-6d2b-4991-bfe5-2038cad1eb46", "generation": 6, "timestamp": 1782660936.8011165, "iteration_found": 0, "metrics": {"combined_score": -0.2573642549002587, "stable_frequency_hitrate": 0.6128750000000001, "churn_hitrate": 0.30779166666666663}, "complexity": 0.0, "diversity": 0.0, "metadata": {"changes": "Full rewrite", "parent_metrics": {"combined_score": -0.24225010061543753, "stable_frequency_hitrate": 0.6053541666666666, "churn_hitrate": 0.31097916666666664}, "island": 3, "migrant": true}, "prompts": null, "artifacts_json": null, "artifact_dir": null, "embedding": null}