{"id": "926ca1c1-067e-43ce-beaf-636e4aaa7913", "code": "# EVOLVE-BLOCK-START\ndef score(age, frequency, recency, size, cache_size, now):\n    \"\"\"\n    Adaptive Hybrid Policy with Logarithmic Age Penalty.\n    \n    Strategy:\n    - Recency (1.0): Primary driver for temporal locality.\n    - Frequency (0.4): Boost for stable popularity, balanced against recency.\n    - Age (Logarithmic): Instead of linear penalty, we use log(age+1). \n      This prevents the premature eviction of items in temporal cycles (like 1..N..1) \n      where 'age' is large but 'recency' is also high (or about to be high), \n      while still allowing eviction in scan/churn workloads.\n    \"\"\"\n    import math\n    # Use log(age + 1) to dampen the penalty for old items, helping temporal locality,\n    # while still increasing cost with age to help with scan/churn.\n    age_factor = math.log(age + 1) / 10.0 \n    return recency + frequency * 0.4 + age_factor\n# EVOLVE-BLOCK-END", "changes_description": null, "language": "python", "parent_id": "bff1b2de-e368-4a79-9d2a-a89e6e5fdb33", "generation": 3, "timestamp": 1782575903.609063, "iteration_found": 122, "metrics": {"combined_score": 0.0}, "complexity": 0.0, "diversity": 0.0, "metadata": {"changes": "Full rewrite", "parent_metrics": {"churn_hitrate": 0.2069375, "combined_score": 0.27415005760119193, "temporal_locality_hitrate": 0.0975, "stable_frequency_hitrate": 0.5959375, "scan_hitrate": 0.49375}, "island": 3}, "prompts": null, "artifacts_json": null, "artifact_dir": null, "embedding": null}